xai_embeddings/__init__.py
xai_embeddings/distances.py
xai_embeddings/explainers/LOO_explainer.py
xai_embeddings/explainers/POS_permutation_explainer.py
xai_embeddings/explainers/__init__.py
xai_embeddings/explainers/attention_explainer.py
xai_embeddings/explainers/explainer.py
xai_embeddings/explainers/explanation.py
xai_embeddings/explainers/subset_explainer.py
xai_embeddings/models/BERT_model.py
xai_embeddings/models/__init__.py
xai_embeddings/models/model.py
xaiembeddings-0.1.3.dist-info/licenses/LICENSE
xaiembeddings-0.1.3.dist-info/METADATA
xaiembeddings-0.1.3.dist-info/WHEEL
xaiembeddings-0.1.3.dist-info/top_level.txt
xaiembeddings-0.1.3.dist-info/RECORD
