Metadata-Version: 2.4
Name: xaiembeddings
Version: 0.1.3
Summary: A Python package for explainable AI embeddings analysis with perturbation-based methods.
Author-email: Bartosz Rybiński <bartoszrybinski@proton.me>
License-Expression: MIT
Project-URL: Homepage, https://github.com/brybinski/xaiEmbeddings
Project-URL: Repository, https://github.com/brybinski/xaiEmbeddings
Requires-Python: >=3.12
License-File: LICENSE
Requires-Dist: torch>=2.0.0
Requires-Dist: transformers>=4.30.0
Requires-Dist: numpy>=1.24.0
Requires-Dist: tqdm>=4.60.0
Requires-Dist: d3blocks>=1.4.11
Requires-Dist: spacy<4.0.0,>=3.7.0
Requires-Dist: scikit-learn>=1.3.0
Requires-Dist: matplotlib>=3.6.0
Dynamic: license-file
